np_log/__init__.py
np_log/log_conf.py
np_log/setup.py
np_log/test.py
np_log/v2.py
np_log/v3.py
np_log/v4.py
np_log-0.2.4.dist-info/LICENSE
np_log-0.2.4.dist-info/METADATA
np_log-0.2.4.dist-info/WHEEL
np_log-0.2.4.dist-info/top_level.txt
np_log-0.2.4.dist-info/RECORD
